pycql/__init__.py
pycql/ast.py
pycql/lexer.py
pycql/lextab.py
pycql/parser.py
pycql/parsetab.py
pycql/util.py
pycql/values.py
pycql/integrations/__init__.py
pycql/integrations/django/__init__.py
pycql/integrations/django/evaluate.py
pycql/integrations/django/filters.py
pycql/integrations/django/parser.py
pycql/integrations/sqlalchemy/__init__.py
pycql/integrations/sqlalchemy/evaluate.py
pycql/integrations/sqlalchemy/filters.py
pycql/integrations/sqlalchemy/parser.py
pycql-0.0.12.dist-info/LICENSE
pycql-0.0.12.dist-info/METADATA
pycql-0.0.12.dist-info/WHEEL
pycql-0.0.12.dist-info/top_level.txt
pycql-0.0.12.dist-info/RECORD
