Metadata-Version: 2.1
Name: pycql
Version: 0.0.12
Summary: pycql is a pure Python parser implementation of the OGC CQL standard
Home-page: https://github.com/geopython/pycql
Author: Fabian Schindler
Author-email: fabian.schindler@gmail.com
License: MIT
Platform: UNKNOWN
Classifier: Development Status :: 3 - Alpha
Classifier: Intended Audience :: Developers
Classifier: Topic :: Scientific/Engineering :: GIS
Classifier: License :: OSI Approved :: MIT License
Classifier: Programming Language :: Python :: 3.5
Classifier: Programming Language :: Python :: 3.6
Classifier: Programming Language :: Python :: 3.7
Requires-Dist: dateparser
Requires-Dist: ply
